{
  "generated_at": "2025-08-28T18:58:03Z",
  "period": "2025-08",
  "entity_scope": "ALL",
  "matches": [
    {
      "ap_bill_id": "AP050023",
      "ar_invoice_id": "AR060025",
      "confidence": 0.85,
      "reason": "Both transactions occurred on 2025-08-17 (Sunday) with the same entity ENT102 and similar currency GBP.",
      "support": {
        "amount_delta": 124849.39,
        "date_gap_days": 0,
        "signals": [
          "date_near",
          "same_entity"
        ]
      }
    },
    {
      "ap_bill_id": "AP050008",
      "ar_invoice_id": "AR060004",
      "confidence": 0.75,
      "reason": "Both transactions are near month-end with the same entity ENT100 and similar currency USD.",
      "support": {
        "amount_delta": 189780.22,
        "date_gap_days": 2,
        "signals": [
          "date_near",
          "same_entity"
        ]
      }
    },
    {
      "ap_bill_id": "AP050006",
      "ar_invoice_id": "AR060016",
      "confidence": 0.7,
      "reason": "Both transactions occurred on a weekend with the same entity ENT100 and similar currency USD.",
      "support": {
        "amount_delta": 220639.64,
        "date_gap_days": 14,
        "signals": [
          "date_near",
          "same_entity"
        ]
      }
    }
  ],
  "unresolved_summary": {
    "ap_exceptions": 19,
    "ar_exceptions": 15
  },
  "citations": [
    "/Users/robertvanraamsdonk/Code/r2r_financial_close_blackline_light/out/run_20250828T185756Z/ap_reconciliation_run_20250828T185756Z.json",
    "/Users/robertvanraamsdonk/Code/r2r_financial_close_blackline_light/out/run_20250828T185756Z/ar_reconciliation_run_20250828T185756Z.json"
  ]
}